yassh/__init__.py
yassh/exceptions.py
yassh/execution.py
yassh/local_run.py
yassh/reactor.py
yassh/remote_configuration.py
yassh/remote_copy.py
yassh/remote_run.py
yassh-2.0.3.dist-info/LICENSE.txt
yassh-2.0.3.dist-info/METADATA
yassh-2.0.3.dist-info/WHEEL
yassh-2.0.3.dist-info/top_level.txt
yassh-2.0.3.dist-info/RECORD
