Metadata-Version: 2.1
Name: yassh
Version: 2.0.3
Summary: A remote process launcher.
Home-page: https://github.com/enyx-opensource/yassh.git
Author: David Keller
Author-email: david.keller@enyx.com
License: BSD
Keywords: process launcher
Platform: UNIX
Requires-Dist: pexpect
